MANIFEST.in
README.rst
setup.py
comname/__init__.py
comname/comname.py
comname/comname_tyc.py
comname/comtags.py
comname/docut_wzc.py
comname/print_bad_types.py
comname/sort_user_dict_industries.py
comname/sort_user_dict_types.py
comname/sort_user_types.py
comname/sort_user_types2.py
comname/update_error.py
comname.egg-info/PKG-INFO
comname.egg-info/SOURCES.txt
comname.egg-info/dependency_links.txt
comname.egg-info/requires.txt
comname.egg-info/top_level.txt
comname/json/com_cities.json
comname/json/com_error_names.json
comname/json/com_names_5w.json
comname/json/com_tails.json
comname/json/com_types.json
comname/user_dict/bad_keys.dat
comname/user_dict/com_name_industry.dat
comname/user_dict/com_name_industry_tags_remap.json
comname/user_dict/com_name_industry_tags_user_dict.dat
comname/user_dict/solo_types.dat
comname/user_dict/user_dict.dat
comname/user_dict/user_dict_com_citys.dat
comname/user_dict/user_dict_com_etypes.dat
comname/user_dict/user_dict_com_etypes.json
comname/user_dict/user_dict_com_etypes_old.json
comname/user_dict/user_dict_com_etypes_weight.json
comname/user_dict/user_dict_com_industries.dat
comname/user_dict/user_dict_com_industries_20190111_17_05_35.dat
comname/user_dict/user_dict_com_industries_20190112_00_40_36.dat
comname/user_dict/user_dict_com_industries_20190112_00_45_19.dat
comname/user_dict/user_dict_com_industries_more.dat
comname/user_dict/user_dict_com_sub_tails.dat
comname/user_dict/user_dict_com_sub_types.dat
comname/user_dict/user_dict_com_tails.dat
comname/user_dict/user_dict_com_types.dat
comname/user_dict/user_dict_com_types_old.dat